LICENSE
MANIFEST.in
README.md
pyproject.toml
setup.cfg
setup.py
tap_yotpo/__init__.py
tap_yotpo/client.py
tap_yotpo/discover.py
tap_yotpo/exceptions.py
tap_yotpo/helpers.py
tap_yotpo/sync.py
tap_yotpo.egg-info/PKG-INFO
tap_yotpo.egg-info/SOURCES.txt
tap_yotpo.egg-info/dependency_links.txt
tap_yotpo.egg-info/entry_points.txt
tap_yotpo.egg-info/requires.txt
tap_yotpo.egg-info/top_level.txt
tap_yotpo/schemas/collections.json
tap_yotpo/schemas/emails.json
tap_yotpo/schemas/order_fulfillments.json
tap_yotpo/schemas/orders.json
tap_yotpo/schemas/product_reviews.json
tap_yotpo/schemas/product_variants.json
tap_yotpo/schemas/products.json
tap_yotpo/schemas/reviews.json
tap_yotpo/schemas/unsubscribers.json
tap_yotpo/streams/__init__.py
tap_yotpo/streams/abstracts.py
tap_yotpo/streams/collections.py
tap_yotpo/streams/emails.py
tap_yotpo/streams/order_fulfillments.py
tap_yotpo/streams/orders.py
tap_yotpo/streams/product_reviews.py
tap_yotpo/streams/product_variants.py
tap_yotpo/streams/products.py
tap_yotpo/streams/reviews.py
tap_yotpo/streams/unsubscribers.py
tests/test_all_fields.py
tests/test_automatic_fields.py
tests/test_bookmark.py
tests/test_discovery.py
tests/test_interrupted_sync.py
tests/test_pagination.py
tests/test_start_date.py