Metadata-Version: 2.1
Name: tap-yotpo
Version: 2.0.1
Summary: Singer.io tap for extracting data from the Yotpo API
Home-page: https://singer.io
Author: Stitch
Classifier: Programming Language :: Python :: 3 :: Only
Provides-Extra: dev
License-File: LICENSE
